CHANGELOG
LICENSE
MANIFEST.in
README.rst
setup.py
markgen/__init__.py
markgen.egg-info/PKG-INFO
markgen.egg-info/SOURCES.txt
markgen.egg-info/dependency_links.txt
markgen.egg-info/top_level.txt