Metadata-Version: 1.1
Name: markgen
Version: 0.9.5
Summary: Python library for the programmatic generation of markdown text
Home-page: https://github.com/1stvamp/markgen.py
Author: Wes Mason
Author-email: wes@1stvamp.org
License: BSD
Platform: UNKNOWN
Provides: markgen
